pyback/__init__.py
pyback/logger.py
pyback/pgsql/__init__.py
pyback/pgsql/pg_config.py
pyback/pgsql/pg_credentials.py
pyback/pgsql/pgsql_async_client.py
pyback/rest/__init__.py
pyback/rest/errors/__init__.py
pyback/rest/errors/bad_request.py
pyback/rest/errors/base_error.py
pyback/rest/errors/forbidden.py
pyback/rest/errors/internal_error.py
pyback/rest/errors/not_found.py
pyback/rest/errors/unauthorized.py
pyback/rest/handlers/__init__.py
pyback/rest/handlers/base_error_handler.py
pyback/rest/responses/__init__.py
pyback/rest/responses/base_response.py
pyback/rest/responses/error.py
pyback/rest/responses/metadata.py
pyback/rest/responses/pagination.py
pyback/rest/responses/response.py
pyback/telemetry/__init__.py
pyback/telemetry/decorator.py
pyback_utils-0.1.1.dist-info/LICENSE
pyback_utils-0.1.1.dist-info/METADATA
pyback_utils-0.1.1.dist-info/WHEEL
pyback_utils-0.1.1.dist-info/top_level.txt
pyback_utils-0.1.1.dist-info/RECORD
